[{"iob":0.842,"activity":0.022,"bolussnooze":0,"basaliob":-0.442,"netbasalinsulin":-0.65,"hightempinsulin":0.4,"time":"2016-07-08T02:35:40.000Z"},{"iob":0.74,"activity":0.0205,"bolussnooze":0,"basaliob":-0.417,"netbasalinsulin":-0.75,"hightempinsulin":0.3,"time":"2016-07-08T02:40:40.000Z"},{"iob":0.594,"activity":0.0192,"bolussnooze":0,"basaliob":-0.443,"netbasalinsulin":-0.85,"hightempinsulin":0.25,"time":"2016-07-08T02:45:40.000Z"},{"iob":0.505,"activity":0.0178,"bolussnooze":0,"basaliob":-0.418,"netbasalinsulin":-0.9,"hightempinsulin":0.2,"time":"2016-07-08T02:50:40.000Z"},{"iob":0.422,"activity":0.0165,"bolussnooze":0,"basaliob":-0.393,"netbasalinsulin":-1,"hightempinsulin":0.1,"time":"2016-07-08T02:55:40.000Z"},{"iob":0.346,"activity":0.0152,"bolussnooze":0,"basaliob":-0.368,"netbasalinsulin":-1,"hightempinsulin":0.05,"time":"2016-07-08T03:00:40.000Z"},{"iob":0.277,"activity":0.014,"bolussnooze":0,"basaliob":-0.344,"netbasalinsulin":-0.95,"hightempinsulin":0.05,"time":"2016-07-08T03:05:40.000Z"},{"iob":0.213,"activity":0.0127,"bolussnooze":0,"basaliob":-0.32,"netbasalinsulin":-0.9,"hightempinsulin":0.05,"time":"2016-07-08T03:10:40.000Z"},{"iob":0.156,"activity":0.0114,"bolussnooze":0,"basaliob":-0.297,"netbasalinsulin":-0.85,"hightempinsulin":0.05,"time":"2016-07-08T03:15:40.000Z"},{"iob":0.106,"activity":0.0101,"bolussnooze":0,"basaliob":-0.273,"netbasalinsulin":-0.85,"hightempinsulin":0.05,"time":"2016-07-08T03:20:40.000Z"},{"iob":0.061,"activity":0.0089,"bolussnooze":0,"basaliob":-0.25,"netbasalinsulin":-0.8,"hightempinsulin":0.05,"time":"2016-07-08T03:25:40.000Z"},{"iob":0.022,"activity":0.0078,"bolussnooze":0,"basaliob":-0.228,"netbasalinsulin":-0.75,"hightempinsulin":0.05,"time":"2016-07-08T03:30:40.000Z"},{"iob":-0.011,"activity":0.0066,"bolussnooze":0,"basaliob":-0.206,"netbasalinsulin":-0.7,"hightempinsulin":0.05,"time":"2016-07-08T03:35:40.000Z"},{"iob":-0.038,"activity":0.0055,"bolussnooze":0,"basaliob":-0.186,"netbasalinsulin":-0.65,"hightempinsulin":0.05,"time":"2016-07-08T03:40:40.000Z"},{"iob":-0.06,"activity":0.0044,"bolussnooze":0,"basaliob":-0.167,"netbasalinsulin":-0.65,"hightempinsulin":0.05,"time":"2016-07-08T03:45:40.000Z"},{"iob":-0.076,"activity":0.0033,"bolussnooze":0,"basaliob":-0.149,"netbasalinsulin":-0.55,"hightempinsulin":0.05,"time":"2016-07-08T03:50:40.000Z"},{"iob":-0.087,"activity":0.0022,"bolussnooze":0,"basaliob":-0.132,"netbasalinsulin":-0.5,"hightempinsulin":0.05,"time":"2016-07-08T03:55:40.000Z"},{"iob":-0.092,"activity":0.0011,"bolussnooze":0,"basaliob":-0.116,"netbasalinsulin":-0.45,"hightempinsulin":0.05,"time":"2016-07-08T04:00:40.000Z"},{"iob":-0.092,"activity":0,"bolussnooze":0,"basaliob":-0.101,"netbasalinsulin":-0.4,"hightempinsulin":0.05,"time":"2016-07-08T04:05:40.000Z"},{"iob":-0.086,"activity":-0.0011,"bolussnooze":0,"basaliob":-0.088,"netbasalinsulin":-0.4,"hightempinsulin":0.05,"time":"2016-07-08T04:10:40.000Z"},{"iob":-0.075,"activity":-0.0023,"bolussnooze":0,"basaliob":-0.075,"netbasalinsulin":-0.4,"hightempinsulin":0.05,"time":"2016-07-08T04:15:40.000Z"},{"iob":-0.063,"activity":-0.0023,"bolussnooze":0,"basaliob":-0.063,"netbasalinsulin":-0.45,"hightempinsulin":0,"time":"2016-07-08T04:20:40.000Z"},{"iob":-0.053,"activity":-0.0021,"bolussnooze":0,"basaliob":-0.053,"netbasalinsulin":-0.4,"hightempinsulin":0,"time":"2016-07-08T04:25:40.000Z"},{"iob":-0.043,"activity":-0.0019,"bolussnooze":0,"basaliob":-0.043,"netbasalinsulin":-0.4,"hightempinsulin":0,"time":"2016-07-08T04:30:40.000Z"},{"iob":-0.035,"activity":-0.0017,"bolussnooze":0,"basaliob":-0.035,"netbasalinsulin":-0.4,"hightempinsulin":0,"time":"2016-07-08T04:35:40.000Z"},{"iob":-0.028,"activity":-0.0014,"bolussnooze":0,"basaliob":-0.028,"netbasalinsulin":-0.4,"hightempinsulin":0,"time":"2016-07-08T04:40:40.000Z"},{"iob":-0.022,"activity":-0.0013,"bolussnooze":0,"basaliob":-0.022,"netbasalinsulin":-0.35,"hightempinsulin":0,"time":"2016-07-08T04:45:40.000Z"},{"iob":-0.016,"activity":-0.0011,"bolussnooze":0,"basaliob":-0.016,"netbasalinsulin":-0.35,"hightempinsulin":0,"time":"2016-07-08T04:50:40.000Z"},{"iob":-0.012,"activity":-0.0009,"bolussnooze":0,"basaliob":-0.012,"netbasalinsulin":-0.35,"hightempinsulin":0,"time":"2016-07-08T04:55:40.000Z"},{"iob":-0.008,"activity":-0.0007,"bolussnooze":0,"basaliob":-0.008,"netbasalinsulin":-0.35,"hightempinsulin":0,"time":"2016-07-08T05:00:40.000Z"},{"iob":-0.006,"activity":-0.0005,"bolussnooze":0,"basaliob":-0.006,"netbasalinsulin":-0.3,"hightempinsulin":0,"time":"2016-07-08T05:05:40.000Z"},{"iob":-0.004,"activity":-0.0004,"bolussnooze":0,"basaliob":-0.004,"netbasalinsulin":-0.2,"hightempinsulin":0,"time":"2016-07-08T05:10:40.000Z"},{"iob":-0.002,"activity":-0.0003,"bolussnooze":0,"basaliob":-0.002,"netbasalinsulin":-0.15,"hightempinsulin":0,"time":"2016-07-08T05:15:40.000Z"},{"iob":-0.001,"activity":-0.0002,"bolussnooze":0,"basaliob":-0.001,"netbasalinsulin":-0.15,"hightempinsulin":0,"time":"2016-07-08T05:20:40.000Z"},{"iob":-0.001,"activity":-0.0001,"bolussnooze":0,"basaliob":-0.001,"netbasalinsulin":-0.1,"hightempinsulin":0,"time":"2016-07-08T05:25:40.000Z"},{"iob":0,"activity":-0.0001,"bolussnooze":0,"basaliob":0,"netbasalinsulin":-0.05,"hightempinsulin":0,"time":"2016-07-08T05:30:40.000Z"}]
