{
  "bg": 101, 
  "temp": "absolute", 
  "snoozeBG": 192, 
  "recieved": true, 
  "predBGs": {
    "IOB": [
      101, 
      111, 
      120, 
      129, 
      137, 
      145, 
      152, 
      159, 
      165, 
      170, 
      175, 
      179, 
      181, 
      184, 
      187, 
      189, 
      191, 
      193, 
      195, 
      196, 
      197, 
      199, 
      199, 
      200, 
      201, 
      202, 
      202, 
      203, 
      203, 
      203, 
      203, 
      204
    ]
  }, 
  "rate": 1.6, 
  "reason": "COB: 0, Dev: 57, BGI: 0.88, ISF: 103.9, Target: 131; Eventual BG 192>=131, adj. req. rate:1.6 to maxSafeBasal:1.6, temp 0.4<1.6U/hr", 
  "COB": 0, 
  "eventualBG": 192, 
  "timestamp": "2016-07-03T01:48:11.131168", 
  "duration": 30, 
  "tick": "+11", 
  "IOB": -0.429
}