{
  "bg": 96, 
  "temp": "absolute", 
  "snoozeBG": 120, 
  "recieved": true, 
  "predBGs": {
    "IOB": [
      96, 
      97, 
      98, 
      99, 
      101, 
      102, 
      104, 
      105, 
      107, 
      108, 
      110, 
      111, 
      113, 
      114, 
      115, 
      116, 
      117, 
      118, 
      119, 
      120, 
      120, 
      121, 
      121, 
      121, 
      122
    ]
  }, 
  "rate": 1.7, 
  "reason": "COB: 0, Dev: -5, BGI: 1.8, ISF: 73.5, Target: 80; Eventual BG 120 >= 80, temp 0.625<1.7U/hr", 
  "COB": 0, 
  "eventualBG": 120, 
  "timestamp": "2016-07-14T12:03:53.568444", 
  "duration": 30, 
  "tick": "+4", 
  "IOB": -0.394
}