{
  "device": "openaps://indy-e1", 
  "pump": {
    "battery": {
      "status": "normal", 
      "voltage": 1.44
    }, 
    "status": {
      "status": "normal", 
      "timestamp": "2016-07-07T19:53:11.000Z", 
      "bolusing": false, 
      "suspended": false
    }, 
    "reservoir": 107.725, 
    "clock": "2016-07-07T12:52:49-07:00"
  }, 
  "openaps": {
    "suggested": {
      "bg": 120, 
      "temp": "absolute", 
      "snoozeBG": 138, 
      "timestamp": "2016-07-07T19:54:30.000Z", 
      "predBGs": {
        "IOB": [
          120, 
          116, 
          111, 
          106, 
          101, 
          94, 
          88, 
          81, 
          73, 
          65, 
          56, 
          47, 
          39
        ]
      }, 
      "reason": "COB: undefined, Dev: 0, BGI: -3.96, ISF: 80, Target: 115; Eventual BG -77<115, bolus snooze: eventual BG range -77-138, temp 0.5 ~ req 0.5U/hr", 
      "eventualBG": -77, 
      "tick": -3, 
      "IOB": 2.463
    }, 
    "iob": [
      {
        "netbasalinsulin": 0.25, 
        "activity": 0.0099, 
        "basaliob": 0.137, 
        "time": "2016-07-07T19:52:49.000Z", 
        "hightempinsulin": 0.8, 
        "bolussnooze": 1.791, 
        "iob": 2.463
      }, 
      {
        "netbasalinsulin": 0.2, 
        "activity": 0.0114, 
        "basaliob": 0.128, 
        "time": "2016-07-07T19:57:49.000Z", 
        "hightempinsulin": 0.75, 
        "bolussnooze": 1.35, 
        "iob": 2.406
      }, 
      {
        "netbasalinsulin": 0.1, 
        "activity": 0.0128, 
        "basaliob": 0.118, 
        "time": "2016-07-07T20:02:49.000Z", 
        "hightempinsulin": 0.65, 
        "bolussnooze": 0.885, 
        "iob": 2.342
      }, 
      {
        "netbasalinsulin": 0, 
        "activity": 0.0142, 
        "basaliob": 0.106, 
        "time": "2016-07-07T20:07:49.000Z", 
        "hightempinsulin": 0.55, 
        "bolussnooze": 0.518, 
        "iob": 2.271
      }, 
      {
        "netbasalinsulin": -0.05, 
        "activity": 0.0156, 
        "basaliob": 0.094, 
        "time": "2016-07-07T20:12:49.000Z", 
        "hightempinsulin": 0.5, 
        "bolussnooze": 0.249, 
        "iob": 2.192
      }, 
      {
        "netbasalinsulin": -0.05, 
        "activity": 0.0168, 
        "basaliob": 0.081, 
        "time": "2016-07-07T20:17:49.000Z", 
        "hightempinsulin": 0.5, 
        "bolussnooze": 0.077, 
        "iob": 2.108
      }, 
      {
        "netbasalinsulin": -0.05, 
        "activity": 0.018, 
        "basaliob": 0.069, 
        "time": "2016-07-07T20:22:49.000Z", 
        "hightempinsulin": 0.5, 
        "bolussnooze": 0.003, 
        "iob": 2.018
      }, 
      {
        "netbasalinsulin": 0, 
        "activity": 0.019, 
        "basaliob": 0.058, 
        "time": "2016-07-07T20:27:49.000Z", 
        "hightempinsulin": 0.5, 
        "bolussnooze": 0, 
        "iob": 1.923
      }, 
      {
        "netbasalinsulin": 0.05, 
        "activity": 0.0201, 
        "basaliob": 0.048, 
        "time": "2016-07-07T20:32:49.000Z", 
        "hightempinsulin": 0.5, 
        "bolussnooze": 0, 
        "iob": 1.823
      }, 
      {
        "netbasalinsulin": 0.05, 
        "activity": 0.0216, 
        "basaliob": 0.039, 
        "time": "2016-07-07T20:37:49.000Z", 
        "hightempinsulin": 0.5, 
        "bolussnooze": 0, 
        "iob": 1.715
      }, 
      {
        "netbasalinsulin": 0.1, 
        "activity": 0.0231, 
        "basaliob": 0.031, 
        "time": "2016-07-07T20:42:49.000Z", 
        "hightempinsulin": 0.5, 
        "bolussnooze": 0, 
        "iob": 1.599
      }, 
      {
        "netbasalinsulin": 0.1, 
        "activity": 0.0246, 
        "basaliob": 0.023, 
        "time": "2016-07-07T20:47:49.000Z", 
        "hightempinsulin": 0.5, 
        "bolussnooze": 0, 
        "iob": 1.476
      }, 
      {
        "netbasalinsulin": 0.1, 
        "activity": 0.0262, 
        "basaliob": 0.017, 
        "time": "2016-07-07T20:52:49.000Z", 
        "hightempinsulin": 0.5, 
        "bolussnooze": 0, 
        "iob": 1.345
      }, 
      {
        "netbasalinsulin": 0.15, 
        "activity": 0.026, 
        "basaliob": 0.011, 
        "time": "2016-07-07T20:57:49.000Z", 
        "hightempinsulin": 0.5, 
        "bolussnooze": 0, 
        "iob": 1.214
      }, 
      {
        "netbasalinsulin": 0.2, 
        "activity": 0.0247, 
        "basaliob": 0.005, 
        "time": "2016-07-07T21:02:49.000Z", 
        "hightempinsulin": 0.5, 
        "bolussnooze": 0, 
        "iob": 1.09
      }, 
      {
        "netbasalinsulin": 0.2, 
        "activity": 0.0234, 
        "basaliob": 0, 
        "time": "2016-07-07T21:07:49.000Z", 
        "hightempinsulin": 0.5, 
        "bolussnooze": 0, 
        "iob": 0.973
      }, 
      {
        "netbasalinsulin": 0.25, 
        "activity": 0.0221, 
        "basaliob": -0.005, 
        "time": "2016-07-07T21:12:49.000Z", 
        "hightempinsulin": 0.5, 
        "bolussnooze": 0, 
        "iob": 0.862
      }, 
      {
        "netbasalinsulin": 0.3, 
        "activity": 0.0207, 
        "basaliob": -0.008, 
        "time": "2016-07-07T21:17:49.000Z", 
        "hightempinsulin": 0.5, 
        "bolussnooze": 0, 
        "iob": 0.759
      }, 
      {
        "netbasalinsulin": 0.35, 
        "activity": 0.0193, 
        "basaliob": -0.011, 
        "time": "2016-07-07T21:22:49.000Z", 
        "hightempinsulin": 0.5, 
        "bolussnooze": 0, 
        "iob": 0.662
      }, 
      {
        "netbasalinsulin": 0.35, 
        "activity": 0.0179, 
        "basaliob": -0.013, 
        "time": "2016-07-07T21:27:49.000Z", 
        "hightempinsulin": 0.5, 
        "bolussnooze": 0, 
        "iob": 0.573
      }, 
      {
        "netbasalinsulin": 0.35, 
        "activity": 0.0165, 
        "basaliob": -0.014, 
        "time": "2016-07-07T21:32:49.000Z", 
        "hightempinsulin": 0.5, 
        "bolussnooze": 0, 
        "iob": 0.49
      }, 
      {
        "netbasalinsulin": 0.35, 
        "activity": 0.0151, 
        "basaliob": -0.015, 
        "time": "2016-07-07T21:37:49.000Z", 
        "hightempinsulin": 0.5, 
        "bolussnooze": 0, 
        "iob": 0.415
      }, 
      {
        "netbasalinsulin": 0.3, 
        "activity": 0.0137, 
        "basaliob": -0.014, 
        "time": "2016-07-07T21:42:49.000Z", 
        "hightempinsulin": 0.45, 
        "bolussnooze": 0, 
        "iob": 0.346
      }, 
      {
        "netbasalinsulin": 0.25, 
        "activity": 0.0124, 
        "basaliob": -0.012, 
        "time": "2016-07-07T21:47:49.000Z", 
        "hightempinsulin": 0.4, 
        "bolussnooze": 0, 
        "iob": 0.284
      }, 
      {
        "netbasalinsulin": 0.15, 
        "activity": 0.011, 
        "basaliob": -0.011, 
        "time": "2016-07-07T21:52:49.000Z", 
        "hightempinsulin": 0.3, 
        "bolussnooze": 0, 
        "iob": 0.229
      }, 
      {
        "netbasalinsulin": 0.05, 
        "activity": 0.0098, 
        "basaliob": -0.008, 
        "time": "2016-07-07T21:57:49.000Z", 
        "hightempinsulin": 0.2, 
        "bolussnooze": 0, 
        "iob": 0.18
      }, 
      {
        "netbasalinsulin": -0.05, 
        "activity": 0.0086, 
        "basaliob": -0.006, 
        "time": "2016-07-07T22:02:49.000Z", 
        "hightempinsulin": 0.1, 
        "bolussnooze": 0, 
        "iob": 0.138
      }, 
      {
        "netbasalinsulin": -0.15, 
        "activity": 0.0074, 
        "basaliob": -0.004, 
        "time": "2016-07-07T22:07:49.000Z", 
        "hightempinsulin": 0, 
        "bolussnooze": 0, 
        "iob": 0.101
      }, 
      {
        "netbasalinsulin": -0.15, 
        "activity": 0.0062, 
        "basaliob": -0.003, 
        "time": "2016-07-07T22:12:49.000Z", 
        "hightempinsulin": 0, 
        "bolussnooze": 0, 
        "iob": 0.07
      }, 
      {
        "netbasalinsulin": -0.15, 
        "activity": 0.0051, 
        "basaliob": -0.001, 
        "time": "2016-07-07T22:17:49.000Z", 
        "hightempinsulin": 0, 
        "bolussnooze": 0, 
        "iob": 0.044
      }, 
      {
        "netbasalinsulin": -0.15, 
        "activity": 0.004, 
        "basaliob": -0.001, 
        "time": "2016-07-07T22:22:49.000Z", 
        "hightempinsulin": 0, 
        "bolussnooze": 0, 
        "iob": 0.024
      }, 
      {
        "netbasalinsulin": -0.1, 
        "activity": 0.0028, 
        "basaliob": 0, 
        "time": "2016-07-07T22:27:49.000Z", 
        "hightempinsulin": 0, 
        "bolussnooze": 0, 
        "iob": 0.01
      }, 
      {
        "netbasalinsulin": -0.05, 
        "activity": 0.0017, 
        "basaliob": 0, 
        "time": "2016-07-07T22:32:49.000Z", 
        "hightempinsulin": 0, 
        "bolussnooze": 0, 
        "iob": 0.002
      }, 
      {
        "netbasalinsulin": -0.05, 
        "activity": 0.0005, 
        "basaliob": 0, 
        "time": "2016-07-07T22:37:49.000Z", 
        "hightempinsulin": 0, 
        "bolussnooze": 0, 
        "iob": 0
      }, 
      {
        "netbasalinsulin": 0, 
        "activity": 0, 
        "basaliob": 0, 
        "time": "2016-07-07T22:42:49.000Z", 
        "hightempinsulin": 0, 
        "bolussnooze": 0, 
        "iob": 0
      }, 
      {
        "netbasalinsulin": 0, 
        "activity": 0, 
        "basaliob": 0, 
        "time": "2016-07-07T22:47:49.000Z", 
        "hightempinsulin": 0, 
        "bolussnooze": 0, 
        "iob": 0
      }
    ], 
    "enacted": {
      "bg": 125, 
      "temp": "absolute", 
      "snoozeBG": 186, 
      "recieved": true, 
      "predBGs": {
        "COB": [
          125, 
          125, 
          125, 
          123, 
          122, 
          119, 
          117, 
          113, 
          109, 
          105, 
          100, 
          95, 
          89, 
          83, 
          76, 
          69, 
          61, 
          55, 
          48, 
          42, 
          39
        ], 
        "aCOB": [
          125, 
          132, 
          138, 
          143, 
          147, 
          151, 
          153, 
          155, 
          157, 
          157, 
          157, 
          156, 
          154, 
          152, 
          149, 
          144, 
          140, 
          136, 
          133, 
          129, 
          126, 
          123, 
          121, 
          118, 
          116, 
          115, 
          113, 
          112, 
          111, 
          110, 
          109, 
          108
        ], 
        "IOB": [
          125, 
          125, 
          124, 
          122, 
          120, 
          116, 
          112, 
          107, 
          101, 
          95, 
          88, 
          80, 
          72, 
          63, 
          53, 
          43, 
          39
        ]
      }, 
      "reason": "COB: 42, Dev: -7, BGI: -2.88, ISF: 80, Target: 115; Eventual BG 39<115, bolus snooze: eventual BG range 39-186; setting current basal of 0.5 as temp. Setting neutral temp basal of 0.5U/hr", 
      "rate": 0.5, 
      "COB": 42, 
      "eventualBG": 39, 
      "timestamp": "2016-07-07T19:46:21.000Z", 
      "duration": 30, 
      "tick": -7, 
      "IOB": 2.494
    }
  }, 
  "mmtune": {
    "scanDetails": [
      [
        "916.564", 
        5, 
        -53
      ], 
      [
        "916.588", 
        5, 
        -47
      ], 
      [
        "916.612", 
        5, 
        -49
      ], 
      [
        "916.636", 
        5, 
        -54
      ], 
      [
        "916.660", 
        5, 
        -52
      ], 
      [
        "916.684", 
        5, 
        -56
      ], 
      [
        "916.708", 
        5, 
        -59
      ]
    ], 
    "setFreq": 916.588, 
    "timestamp": "2016-07-07T19:52:50.000Z", 
    "usedDefault": false
  }
}